MANIFEST.in
README.md
requirements.txt
setup.cfg
setup.py
versioneer.py
botcity/plugins/http/__init__.py
botcity/plugins/http/_version.py
botcity/plugins/http/plugin.py
botcity_http_plugin.egg-info/PKG-INFO
botcity_http_plugin.egg-info/SOURCES.txt
botcity_http_plugin.egg-info/dependency_links.txt
botcity_http_plugin.egg-info/requires.txt
botcity_http_plugin.egg-info/top_level.txt
tests/test_import.py
tests/test_plugin.py