Metadata-Version: 2.1
Name: botcity-http-plugin
Version: 0.1.4
Home-page: https://bitbucket.org/botcitydev/bot-http-plugin-python.git
Requires-Python: >=3.7
